{
    "projects": [
      {
        "category": "CSS",
        "name": "CSS Project 1",
        "description": "A creative CSS project.",
        "images": ["images/symphonycss.png", "images/letterheadcss.png"]
      },
      {
        "category": "HTML",
        "name": "HTML Project 1",
        "description": "An elegant HTML project.",
        "images": ["images/encyclopediahtml.png", "images/letterheadhtml.png"]
      },
      {
        "category": "JS",
        "name": "JS Project 1",
        "description": "An interactive JS project.",
        "images": ["images/factsjs.png", "images/imagejs.png"]
      }
    ]
  }
  